rag_evaluation/__init__.py
rag_evaluation/config.py
rag_evaluation/evaluator.py
rag_evaluation/metrics.py
rag_evaluation/utils.py
rag_evaluation-0.2.3.dist-info/licenses/LICENSE
rag_evaluation-0.2.3.dist-info/METADATA
rag_evaluation-0.2.3.dist-info/WHEEL
rag_evaluation-0.2.3.dist-info/top_level.txt
rag_evaluation-0.2.3.dist-info/RECORD
