Metadata-Version: 2.4
Name: rag_evaluation
Version: 0.2.3
Summary: A robust Python package for evaluating Retrieval-Augmented Generation (RAG) systems.
Author-email: Ola Akindele <akindele.ok@gmail.com>
License-Expression: MIT
Project-URL: Homepage, https://github.com/OlaAkindele/rag_evaluation
Keywords: rag,nlp,evaluation
Classifier: Development Status :: 3 - Alpha
Classifier: Programming Language :: Python :: 3.10
Classifier: Intended Audience :: Developers
Classifier: Topic :: Scientific/Engineering :: Artificial Intelligence
Requires-Python: >=3.10
License-File: LICENSE
Requires-Dist: numpy>=1.25
Requires-Dist: pandas>=2.0
Requires-Dist: python-dotenv>=0.21
Requires-Dist: openai<2,>=1.58.1
Requires-Dist: google-genai<2,>=1.15
Requires-Dist: httpx<1,>=0.28.1
Requires-Dist: transformers>=4.30.0
Requires-Dist: torch>=2.0.0
Requires-Dist: accelerate>=0.20.0
Requires-Dist: sentencepiece>=0.1.97
Requires-Dist: protobuf>=3.20.0
Dynamic: license-file
